prolog_primitives/__init__.py
prolog_primitives/basic/DBManager.py
prolog_primitives/basic/DistributedElements.py
prolog_primitives/basic/PrimitiveWrapper.py
prolog_primitives/basic/Session.py
prolog_primitives/basic/SubRequestEvent.py
prolog_primitives/basic/Utils.py
prolog_primitives/basic/__init__.py
prolog_primitives/basic/filterKbPrimitive.py
prolog_primitives/basic/nt.py
prolog_primitives/generatedProto/__init__.py
prolog_primitives/generatedProto/basicMessages_pb2.py
prolog_primitives/generatedProto/basicMessages_pb2_grpc.py
prolog_primitives/generatedProto/errorsMessages_pb2.py
prolog_primitives/generatedProto/errorsMessages_pb2_grpc.py
prolog_primitives/generatedProto/primitiveService_pb2.py
prolog_primitives/generatedProto/primitiveService_pb2_grpc.py
prolog_primitives/generatedProto/sideEffectsMessages_pb2.py
prolog_primitives/generatedProto/sideEffectsMessages_pb2_grpc.py
prolog_primitives/ml_lib/__init__.py
prolog_primitives/ml_lib/__main__.py
prolog_primitives/ml_lib/collections.py
prolog_primitives/ml_lib/launcher.py
prolog_primitives/ml_lib/dataset/__init__.py
prolog_primitives/ml_lib/dataset/cell.py
prolog_primitives/ml_lib/dataset/column.py
prolog_primitives/ml_lib/dataset/fold.py
prolog_primitives/ml_lib/dataset/randomSplit.py
prolog_primitives/ml_lib/dataset/row.py
prolog_primitives/ml_lib/dataset/theoryToDataset.py
prolog_primitives/ml_lib/dataset/theory_from_Dataset.py
prolog_primitives/ml_lib/neuralNetwork/__init__.py
prolog_primitives/ml_lib/neuralNetwork/denseLayer.py
prolog_primitives/ml_lib/neuralNetwork/inputLayer.py
prolog_primitives/ml_lib/neuralNetwork/neuralNetwork.py
prolog_primitives/ml_lib/neuralNetwork/outputLayer.py
prolog_primitives/ml_lib/predictors/__init__.py
prolog_primitives/ml_lib/predictors/classify.py
prolog_primitives/ml_lib/predictors/predict.py
prolog_primitives/ml_lib/predictors/score.py
prolog_primitives/ml_lib/predictors/train.py
prolog_primitives/ml_lib/schema/__init__.py
prolog_primitives/ml_lib/schema/schema.py
prolog_primitives-1.2.2.dist-info/LICENSE
prolog_primitives-1.2.2.dist-info/METADATA
prolog_primitives-1.2.2.dist-info/WHEEL
prolog_primitives-1.2.2.dist-info/top_level.txt
prolog_primitives-1.2.2.dist-info/RECORD
